EmbedUtils/__init__.py
EmbedUtils/module.py
embedutils-0.2.9.dist-info/METADATA
embedutils-0.2.9.dist-info/WHEEL
embedutils-0.2.9.dist-info/top_level.txt
embedutils-0.2.9.dist-info/RECORD
