Metadata-Version: 2.4
Name: EmbedUtils
Version: 0.2.9
Summary: Library for converting dicts to embeds
Author: MildlyObesePanda
License: MIT
Project-URL: Homepage, https://github.com/krexxy/embedutils
Requires-Dist: requests
Requires-Dist: discord
Requires-Dist: asyncio
